certbot_dns_godaddy.py
certbot_dns_godaddy-2.8.0.dist-info/LICENSE.txt
certbot_dns_godaddy-2.8.0.dist-info/METADATA
certbot_dns_godaddy-2.8.0.dist-info/WHEEL
certbot_dns_godaddy-2.8.0.dist-info/entry_points.txt
certbot_dns_godaddy-2.8.0.dist-info/RECORD
