Metadata-Version: 2.1
Name: certbot-dns-godaddy
Version: 2.8.0
Summary: A certbot plugin that implements letsencrypt dns wildcard support for godaddy using lexicon
Home-page: https://github.com/miigotu/certbot-dns-godaddy
License: Apache-2.0
Author: Dustyn Gibson
Author-email: miigotu@gmail.com
Requires-Python: >=3.8,<4.0
Classifier: Development Status :: 3 - Alpha
Classifier: Environment :: Plugins
Classifier: Intended Audience :: System Administrators
Classifier: License :: OSI Approved :: Apache Software License
Classifier: Operating System :: OS Independent
Classifier: Programming Language :: Python :: 3
Classifier: Programming Language :: Python :: 3.8
Classifier: Programming Language :: Python :: 3.9
Classifier: Programming Language :: Python :: 3.10
Classifier: Programming Language :: Python :: 3.11
Classifier: Programming Language :: Python :: 3.12
Classifier: Programming Language :: Python :: 3 :: Only
Classifier: Topic :: Internet :: WWW/HTTP
Classifier: Topic :: Security
Classifier: Topic :: System :: Installation/Setup
Classifier: Topic :: System :: Networking
Classifier: Topic :: System :: Systems Administration
Classifier: Topic :: Utilities
Requires-Dist: certbot (>=2.8.0)
Requires-Dist: dns-lexicon (>=3.14.0)
Project-URL: Repository, https://github.com/miigotu/certbot-dns-godaddy
